{
  "project_info": {
    "project_number": "657955651810",
    "project_id": "greendme-8e44c",
    "storage_bucket": "greendme-8e44c.firebasestorage.app"
  },
  "client": [
    {
      "client_info": {
        "mobilesdk_app_id": "1:657955651810:android:19c04ae0fe2a6440ae5ebb",
        "android_client_info": {
          "package_name": "com.example.greedme_flutter"
        }
      },
      "oauth_client": [],
      "api_key": [
        {
          "current_key": "AIzaSyDlCXbwRGwWC-_YATRsO0Mtvy9X9nKQloQ"
        }
      ],
      "services": {
        "appinvite_service": {
          "other_platform_oauth_client": []
        }
      }
    }
  ],
  "configuration_version": "1"
}